migration_sql/__init__.py
migration_sql/db.py
migration_sql/migrate.py
migration_sql/schema_version.py
migration_sql/utils.py
migration_sql/version.py
migration_sql/version_helper.py
migration_sql-0.0.13.dist-info/METADATA
migration_sql-0.0.13.dist-info/RECORD
migration_sql-0.0.13.dist-info/WHEEL
migration_sql-0.0.13.dist-info/top_level.txt
